{"cameraMode":{"drawMode":0,"name":"Shaded","section":"Shading Mode"},"sceneLighting":false,"audioPlay":false,"sceneViewState":{"m_AlwaysRefresh":false,"showFog":true,"showSkybox":false,"showFlares":true,"showImageEffects":true,"showParticleSystems":true,"showVisualEffectGraphs":true,"m_FxEnabled":true},"in2DMode":false,"pivot":{"x":73.41609191894531,"y":12.800145149230957,"z":-62.807106018066409},"rotation":{"x":-0.5644011497497559,"y":-0.13571102917194367,"z":0.09508182108402252,"w":-0.8088110685348511},"size":12.899304389953614,"orthographic":false}